{
  "tradingStatus": {
    "state": "BUY_ORDER_PLACED",
    "symbol": "ETH/USDT",
    "currentTradeId": "trade_1769062017785",
    "buyOrder": {
      "orderId": "42007960788",
      "symbol": "ETH/USDT",
      "side": "buy",
      "price": 2995.06,
      "amount": 0.0333,
      "status": "open",
      "createdAt": 1769062017785
    },
    "high": 3038.33,
    "low": 2990.26,
    "lastUpdateTime": 1769062017785
  },
  "tradeRecords": [
    {
      "id": "trade_1768978874800",
      "symbol": "BNB/USDT",
      "buyOrderId": "10814907699",
      "buyPrice": 877.5,
      "amount": 0.113,
      "startTime": 1768978874800,
      "status": "completed",
      "sellOrderId": "10816732774",
      "sellPrice": 878.8,
      "profit": 0.15,
      "profitRate": 0.15,
      "endTime": 1769004644708
    },
    {
      "id": "trade_1769011217672",
      "symbol": "SOL/USDT",
      "buyOrderId": "16120640411",
      "buyPrice": 126.57,
      "amount": 0.79,
      "startTime": 1769011217672,
      "status": "completed",
      "sellOrderId": "16123757413",
      "sellPrice": 130.71,
      "profit": 3.27,
      "profitRate": 3.27,
      "endTime": 1769024297355
    },
    {
      "id": "trade_1769062017785",
      "symbol": "ETH/USDT",
      "buyOrderId": "42007960788",
      "buyPrice": 2995.06,
      "amount": 0.0333,
      "startTime": 1769062017785,
      "status": "in_progress"
    }
  ],
  "lastSaved": 1769062017786
}